Q2/Q2.v
`timescale 1ns/1ps
module Q2(A, B, C, D, Z);
  input wire A, B, C, D;
  output wire Z;
  wire E, F, S1, S2, S3;
  assign #5 S1 = A & B & C;
  assign #5 E = S1 | D;
  assign #5 S2 = B ~| C;
  assign #5 F = S2 ~& A;
  assign #2 S3 = ~F;
  assign #5 Z = E ^ S3;
endmodule

Q2/Q2_tb.v
`timescale 1ns / 1ps
module Q2_tb();
  reg A, B, C, D;
  wire Z;
  
  Q2 uut(A, B, C, D, Z);
  initial
    begin
      $dumpfile("Q2_tb.vcd");
      $dumpvars(0, Q2_tb);
      A = 0; B = 0; C = 0; D = 0;
      #1 D = 1;
      #20 A = 1;
      #23 B = 1;
      #60 $finish;
    end
endmodule

Q2/Q2_tb.vcd
$date
	Mon Jul 12 16:48:41 2021
$end
$version
	Icarus Verilog
$end
$timescale
	1ps
$end
$scope module Q2_tb $end
$var wire 1 ! Z $end
$var reg 1 " A $end
$var reg 1 # B $end
$var reg 1 $ C $end
$var reg 1 % D $end
$scope module uut $end
$var wire 1 & A $end
$var wire 1 ' B $end
$var wire 1 ( C $end
$var wire 1 ) D $end
$var wire 1 * E $end
$var wire 1 + F $end
$var wire 1 , S1 $end
$var wire 1 - S2 $end
$var wire 1 . S3 $end
$var wire 1 ! Z $end
$upscope $end
$upscope $end
$enddefinitions $end
#0
$dumpvars
z.
z-
z,
z+
x*
0)
0(
0'
0&
0%
0$
0#
0"
x!
$end
#1000
1%
1)
#5000
1+
1-
0,
#6000
1*
#7000
0.
#12000
1!
#21000
1"
1&
#26000
0+
#28000
1.
#33000
0!
#44000
1#
1'
#49000
0-
#54000
1+
#56000
0.
#61000
1!
